{
  "title": "بنك أسئلة الوحدة السادسة",
  "questions": [
    {
      "id": 1,
      "text": "ما اتصل إسناده بنقل العدل الذي خف ضبطه عن ضبط رجل الصحيح، ولم يكن شاذاً ولا معللاً، هو تعريف للحديث:",
      "options": [
        "الصحيح لغيره",
        "الحسن لذاته",
        "الضعيف المنجبر",
        "الصحيح لذاته"
      ],
      "correctAnswer": 1
    },
    {
      "id": 2,
      "text": "كيف تتفاوت مراتب الحديث عند المحدثين؟",
      "options": [
        "تبعاً لتفاوت الرواة في العدالة والضبط",
        "تبعاً لمكانة المؤلف في العلم والتقوى",
        "تبعاً لكثرة الأحاديث أو قلتها في الباب",
        "تبعاً لزمن الرواية في العصور الأولى"
      ],
      "correctAnswer": 0
    },
    {
      "id": 3,
      "text": "المرتبة الوسيطة بين الصحيح المتميز برجاله الحفاظ، وبين الضعيف الذي لا يصلح للاحتجاج، هي مرتبة الحديث:",
      "options": [
        "المتروك",
        "الموضوع",
        "الحسن",
        "المنكر"
      ],
      "correctAnswer": 2
    },
    {
      "id": 4,
      "text": "ينقسم الحديث الحسن إلى نوعين رئيسيين، هما:",
      "options": [
        "الحسن لذاته والحسن لغيره",
        "الحسن المقبول والحسن المردود",
        "الحسن المتصل والحسن المرسل",
        "الحسن القوي والحسن الضعيف"
      ],
      "correctAnswer": 0
    },
    {
      "id": 5,
      "text": "الحديث الذي يوصف راويه بأنه \"صدوق\" وهو دون \"الحافظ المتقن الثقة\"، ويقل ضبطه عن رجل الصحيح، هو الحديث:",
      "options": [
        "الصحيح",
        "الحسن لذاته",
        "الحسن لغيره",
        "الضعيف"
      ],
      "correctAnswer": 1
    },
    {
      "id": 6,
      "text": "سُمي الحديث \"الحسن لذاته\" بهذا الاسم لأن:",
      "options": [
        "صفة الحسن اكتسبت من السند نفسه دون قرينة خارجية",
        "صفة الحسن جاءت من خارجه بقرائن وشواهد متعددة",
        "رواته من الثقات الحفاظ في أعلى درجات الضبط والإتقان",
        "رجاله من طبقة كبار الصحابة العدول المتقنين"
      ],
      "correctAnswer": 0
    },
    {
      "id": 7,
      "text": "\"خبر متصل قل ضبط راويه العدل وارتفع عن حال من يعد تفرده منكراً\"، هو تعريف للحسن عند:",
      "options": [
        "ابن الصلاح",
        "ابن رجب الحنبلي",
        "الإمام الذهبي",
        "الشيخ تقي الدين الشمني"
      ],
      "correctAnswer": 3
    },
    {
      "id": 8,
      "text": "الفرق الرئيسي بين تعريف الحديث الصحيح وتعريف الحديث الحسن (كما عند الشمني) يكمن في:",
      "options": [
        "اشتراط اتصال السند في الصحيح دون الحسن",
        "قلة ضبط الراوي في الحسن عن درجة الصحيح",
        "اشتراط السلامة من الشذوذ في الصحيح فقط",
        "اشتراط السلامة من العلة في الصحيح فقط"
      ],
      "correctAnswer": 1
    },
    {
      "id": 9,
      "text": "\"أن يكون راويه من المشهورين بالصدق والأمانة، غير أنه لم يبلغ درجة رجال الصحيح\"، هذا القول في تعريف الحسن منسوب إلى:",
      "options": [
        "ابن رجب الحنبلي",
        "الإمام الترمذي",
        "ابن الصلاح",
        "الإمام النسائي"
      ],
      "correctAnswer": 2
    },
    {
      "id": 10,
      "text": "من هو العالم الحنبلي (ت 795هـ) الذي طبق مراتب الرواة (الصحيح والحسن والضعيف) على طبقات أصحاب الزهري؟",
      "options": [
        "ابن القيم الجوزية",
        "ابن رجب الحنبلي",
        "ابن كثير الدمشقي",
        "ابن تيمية الحراني"
      ],
      "correctAnswer": 1
    },
    {
      "id": 11,
      "text": "من هو الإمام (ت 124هـ) الذي يُعد من الأعلام الذين حفظوا السنة، وقسّم ابن رجب الرواة عنه إلى خمس طبقات؟",
      "options": [
        "الإمام مالك بن أنس",
        "الإمام أحمد بن حنبل",
        "محمد بن مسلم بن شهاب الزهري",
        "الإمام سفيان الثوري"
      ],
      "correctAnswer": 2
    },
    {
      "id": 12,
      "text": "الطبقة الأولى من أصحاب الزهري الذين جمعوا الحفظ والإتقان وطول الصحبة (مثل مالك وابن عيينة) يُصنف حديثهم بأنه:",
      "options": [
        "حسن لغيره",
        "ضعيف",
        "حسن لذاته",
        "صحيح"
      ],
      "correctAnswer": 3
    },
    {
      "id": 13,
      "text": "الطبقة الثالثة من أصحاب الزهري الذين لازموه ولكن \"تكلم في حفظهم\" (مثل محمد بن إسحاق)، هم الذين يؤلفون رجال الحديث:",
      "options": [
        "الصحيح",
        "الحسن",
        "الضعيف",
        "الموضوع"
      ],
      "correctAnswer": 1
    },
    {
      "id": 14,
      "text": "الخلل عند رجال الحديث الحسن (الطبقة الثالثة من أصحاب الزهري) هو في جانب:",
      "options": [
        "الدين والأمانة والصدق",
        "الحفظ والإتقان والضبط",
        "العقيدة والمنهج السلفي",
        "ملازمة الشيخ والسماع منه"
      ],
      "correctAnswer": 1
    },
    {
      "id": 15,
      "text": "الحديث الذي ينزل رجال إسناده عن \"الحسن لذاته\" ويكون فيهم من كثر خطؤهم، ولكنهم لم يصلوا لدرجة المغفلين، هو:",
      "options": [
        "الحسن لغيره",
        "الحسن لذاته",
        "الصحيح لغيره",
        "الضعيف جداً"
      ],
      "correctAnswer": 0
    },
    {
      "id": 16,
      "text": "سُمي الحديث \"الحسن لغيره\" بهذا الاسم لأنه:",
      "options": [
        "يكتسب الحسن من خارجه بفضل القرائن والشواهد",
        "يكتسب الحسن من ذات السند وقوة رجاله",
        "يكون جميع رجاله من الثقات الحفاظ المتقنين",
        "يكون مقبولاً عند الجمهور دون غيرهم من العلماء"
      ],
      "correctAnswer": 0
    },
    {
      "id": 17,
      "text": "\"كل حديث يُروى لا يكون في رواته من يتهم بالكذب، ولا يكون الحديث شاذاً، ويروى من غير وجه نحو ذلك\"، هذا تعريف الإمام الترمذي للحديث:",
      "options": [
        "الصحيح",
        "الحسن",
        "الغريب",
        "المقبول"
      ],
      "correctAnswer": 1
    },
    {
      "id": 18,
      "text": "ما هو حكم الحديث الحسن بنوعيه (لذاته ولغيره)؟",
      "options": [
        "صالح للاحتجاج وتثبت به الأحكام كالصحيح",
        "لا يصلح للاحتجاج في الحلال والحرام",
        "يُعمل به في الفضائل فقط دون الأحكام",
        "يُعتبر من الأحاديث الضعيفة التي لا يُعمل بها"
      ],
      "correctAnswer": 0
    },
    {
      "id": 19,
      "text": "جميع ما يلي يعد من كتب السنن الأربعة التي هي من مصادر الحديث الحسن، ما عدا:",
      "options": [
        "جامع الترمذي",
        "سنن أبي داود",
        "سنن النسائي",
        "موطأ الإمام مالك"
      ],
      "correctAnswer": 3
    },
    {
      "id": 20,
      "text": "من هو مؤلف كتاب \"جامع الترمذي\" (209-279هـ)؟",
      "options": [
        "أبو عيسى محمد بن عيسى الترمذي",
        "أبو داود سليمان بن الأشعث",
        "أبو عبد الرحمن أحمد بن شعيب النسائي",
        "أبو عبد الله محمد بن يزيد بن ماجه"
      ],
      "correctAnswer": 0
    },
    {
      "id": 21,
      "text": "ارتحل الإمام الترمذي إلى خراسان والعراق والحرمين، ولكنه لم يرحل إلى:",
      "options": [
        "مصر والشام",
        "الأندلس والمغرب",
        "الهند وفارس",
        "اليمن وعُمان"
      ],
      "correctAnswer": 0
    },
    {
      "id": 22,
      "text": "سُمي كتاب الترمذي بـ \"الجامع\" لأنه:",
      "options": [
        "لم يقتصر على أبواب الأحكام وتناول موضوعات أخرى",
        "جمع كل الأحاديث الصحيحة الواردة عن النبي",
        "أول كتاب جمع بين الفقه والحديث والتفسير",
        "الكتاب الوحيد الذي اعتمده جميع أهل العلم"
      ],
      "correctAnswer": 0
    },
    {
      "id": 23,
      "text": "ما هو الاسم الذي أطلقه الترمذي على الجزء الذي ختم به كتابه، والذي يبين منهجه ومصطلحاته؟",
      "options": [
        "المقدمة",
        "العلل الصغير",
        "الشمائل المحمدية",
        "العلل الكبير"
      ],
      "correctAnswer": 1
    },
    {
      "id": 24,
      "text": "يُعد الإمام الترمذي هو أول من:",
      "options": [
        "اشترط اتصال السند في الحديث",
        "ألف في علم الجرح والتعديل",
        "أصل للحديث الحسن وجعل كتابه أصلاً له",
        "رتب الأحاديث على الأبواب الفقهية"
      ],
      "correctAnswer": 2
    },
    {
      "id": 25,
      "text": "وصف الإمام الترمذي حديث \"إنما الأعمال بالنية\" في جامعه بأنه:",
      "options": [
        "غريب فقط",
        "حسن صحيح",
        "حسن غريب",
        "صحيح فقط"
      ],
      "correctAnswer": 1
    },
    {
      "id": 26,
      "text": "عندما يقول الترمذي \"حسن صحيح\"، فهذا يعني أن:",
      "options": [
        "الحديث له إسنادان أحدهما حسن والآخر صحيح",
        "الحد الأدنى للحديث هو الحسن والأعلى مفتوح ليشمل الصحيح",
        "هناك شك من الترمذي في درجة الحديث بين الحسن والصحيح",
        "الحديث حسن في متنه وصحيح في سنده فقط"
      ],
      "correctAnswer": 1
    },
    {
      "id": 27,
      "text": "اشترط الإمام الترمذي للفصل بين الحسن والضعيف المردود، أن لا يشتغل بالرواية عن:",
      "options": [
        "الراوي المتهم بالكذب أو المغفل الذي يخطئ كثيراً",
        "الراوي الذي يروي الأحاديث بالمعنى دون اللفظ",
        "الراوي الثقة الذي يروي عن شيوخ لم يلقهم",
        "الراوي الصدوق الذي يروي المناكير أحياناً"
      ],
      "correctAnswer": 0
    },
    {
      "id": 28,
      "text": "ما هو النقد الأساسي الذي وُجه للإمام الترمذي من بعض العلماء كالذهبي؟",
      "options": [
        "التشدد في قبول الرواة والتحسين",
        "التساهل في التصحيح والتحسين والأخذ عن الضعفاء",
        "الإكثار من الأحاديث الغريبة والشاذة",
        "إهمال ذكر العلل في الأحاديث التي يرويها"
      ],
      "correctAnswer": 1
    },
    {
      "id": 29,
      "text": "من هو الإمام (ت 748هـ) الذي انتقد تساهل الترمذي في التصحيح والتحسين؟",
      "options": [
        "ابن رجب الحنبلي",
        "ابن الصلاح الشهرزوري",
        "شمس الدين الذهبي",
        "ابن حجر العسقلاني"
      ],
      "correctAnswer": 2
    },
    {
      "id": 30,
      "text": "ضرب الإمام الذهبي مثلاً على تساهل الترمذي بتحسينه لأحاديث راوٍ مُجَرَّح، هو:",
      "options": [
        "كثير بن عبد الله بن عمرو المزني",
        "محمد بن إسحاق بن يسار",
        "يحيى بن سعيد الأنصاري",
        "سفيان بن حسين الواسطي"
      ],
      "correctAnswer": 0
    },
    {
      "id": 31,
      "text": "دافع الإمام ابن رجب عن الترمذي في إخراجه لحديث \"كثير بن عبد الله المزني\" بأن:",
      "options": [
        "الذهبي أخطأ في نسبة الحديث للترمذي",
        "الترمذي لم يحسن حديثه بل رواه فقط",
        "هذا الراوي لم يُجمع على ترك حديثه بل قواه قوم",
        "الترمذي كان يروي عن الجميع ثم يبين حالهم"
      ],
      "correctAnswer": 2
    },
    {
      "id": 32,
      "text": "من هو مؤلف كتاب \"السنن\" (202-275هـ) الذي كان أحد حفاظ الإسلام، وارتحل لجمع الحديث وهو دون العشرين؟",
      "options": [
        "أبو عيسى الترمذي",
        "أبو داود السجستاني",
        "أبو عبد الرحمن النسائي",
        "أبو عبد الله بن ماجه"
      ],
      "correctAnswer": 1
    },
    {
      "id": 33,
      "text": "\"أُلين لأبي داود الحديث كما أُلين لداود عليه السلام الحديد\"، هذا القول وصف به إبراهيم الحربي الإمام:",
      "options": [
        "الترمذي",
        "البخاري",
        "أبا داود",
        "مسلماً"
      ],
      "correctAnswer": 2
    },
    {
      "id": 34,
      "text": "كم بلغ عدد الأحاديث المتصلة في كتاب \"سنن أبي داود\"؟",
      "options": [
        "ألف حديث متصل",
        "أربعة آلاف وثمانمائة حديث متصل",
        "تسعة آلاف حديث متصل",
        "ستمائة حديث متصل فقط"
      ],
      "correctAnswer": 1
    },
    {
      "id": 35,
      "text": "جاء العدد الكبير للأحاديث في سنن أبي داود بسبب:",
      "options": [
        "منهجه في إدخال أحاديث قويت بغيرها وأحاديث ضعيفة",
        "اقتصاره على الأحاديث الصحيحة فقط دون غيرها",
        "تكرار الأحاديث بأسانيدها المختلفة في كل باب",
        "جمعه لكل ما ورد في السيرة والتاريخ والأحكام"
      ],
      "correctAnswer": 0
    },
    {
      "id": 36,
      "text": "ما كان فيه وهن غير شديد وسكت عنه أبو داود في كتابه، فإنه:",
      "options": [
        "يتركه ولا يحتج به",
        "يعتبره في درجة الصحيح",
        "يعتبره صالحاً للاحتجاج",
        "يذكره للاستشهاد فقط"
      ],
      "correctAnswer": 2
    },
    {
      "id": 37,
      "text": "مصطلح \"صالح\" عند الإمام أبي داود (في قوله: وما لم أذكر فيه شيئاً فهو صالح) يساوي مصطلح:",
      "options": [
        "\"الحسن\" عند الترمذي",
        "\"الضعيف\" عند الجمهور",
        "\"الصحيح\" عند البخاري",
        "\"الغريب\" عند النسائي"
      ],
      "correctAnswer": 0
    },
    {
      "id": 38,
      "text": "بماذا يمتاز كتاب \"سنن أبي داود\" فيما يتعلق بالتبويب؟",
      "options": [
        "ذكر دقائق المسائل والفروع والتفاصيل",
        "الاقتصار على الأبواب الكبرى دون تفريع",
        "ترتيب الأحاديث على مسانيد الصحابة",
        "الترتيب الأبجدي للرواة والمصنفات"
      ],
      "correctAnswer": 0
    },
    {
      "id": 39,
      "text": "من هو مؤلف \"السنن\" الإمام أبو عبد الرحمن (215-303هـ) الذي ولد بـ (نسا) واستوطن مصر؟",
      "options": [
        "أبو عيسى الترمذي",
        "أبو داود السجستاني",
        "أبو عبد الرحمن النسائي",
        "أبو عبد الله بن ماجه"
      ],
      "correctAnswer": 2
    },
    {
      "id": 40,
      "text": "كتاب السنن للإمام النسائي (أحد الكتب الستة) هو في الحقيقة كتاب \"المجتبى\" وهو:",
      "options": [
        "نسخة من السنن الكبرى دون أي تعديل",
        "كتاب أكبر من السنن الكبرى وأكثر تفصيلاً",
        "كتاب مُهذب ومُجتبى (مُختار) من السنن الكبرى",
        "كتاب مختلف تماماً عن السنن الكبرى في المنهج"
      ],
      "correctAnswer": 2
    },
    {
      "id": 41,
      "text": "يُعتبر كتاب \"سنن النسائي\" (المجتبى) من أنقى كتب السنن الأربعة من حيث:",
      "options": [
        "الأسانيد وسلامتها",
        "كثرة الأحاديث الغريبة",
        "عدد الأحاديث الضعيفة",
        "التبويب الفقهي الدقيق"
      ],
      "correctAnswer": 0
    },
    {
      "id": 42,
      "text": "القسم الثالث من كتاب النسائي، حسب تقسيم المقدسي، يحتوي على أحاديث:",
      "options": [
        "مخرجة في الصحيحين",
        "صحيحة على شرط الشيخين",
        "أبان عن علتها بما يفهمه أهل المعرفة",
        "ضعيفة جداً وموضوعة"
      ],
      "correctAnswer": 2
    },
    {
      "id": 43,
      "text": "من هو مؤلف \"السنن\" الإمام أبو عبد الله (209-273 هـ) الذي ارتحل إلى بلاد فارس والعراق ومصر؟",
      "options": [
        "أبو عيسى الترمذي",
        "أبو داود السجستاني",
        "أبو عبد الرحمن النسائي",
        "أبو عبد الله بن ماجه"
      ],
      "correctAnswer": 3
    },
    {
      "id": 44,
      "text": "يُصنف كتاب \"سنن ابن ماجه\" بأنه أقرب إلى الكتاب \"الجامع\"؛ لأنه:",
      "options": [
        "ضم الأحكام وموضوعات أخرى كالأدب والفتن والزهد",
        "الكتاب الوحيد المعتمد لدى جميع المذاهب الفقهية",
        "اقتصر على أحاديث الأحكام الفقهية العملية فقط",
        "جمع كل الأحاديث الصحيحة والحسنة والضعيفة"
      ],
      "correctAnswer": 0
    },
    {
      "id": 45,
      "text": "كانت كتب الحديث المشهورة تعرف بـ \"الكتب الخمسة\" قبل إضافة كتاب:",
      "options": [
        "سنن أبي داود",
        "جامع الترمذي",
        "سنن ابن ماجه",
        "سنن النسائي"
      ],
      "correctAnswer": 2
    },
    {
      "id": 46,
      "text": "من هو أول من أضاف \"سنن ابن ماجه\" للكتب الستة (ت 507هـ)؟",
      "options": [
        "محمد بن طاهر المقدسي",
        "الحافظ عبد الغني المقدسي",
        "الإمام شمس الدين الذهبي",
        "الإمام ابن حجر العسقلاني"
      ],
      "correctAnswer": 0
    },
    {
      "id": 47,
      "text": "\"الكتب التي تجمع روايات الحديث الواحد عن الصحابي الواحد من مواضع مختلفة من الكتب\"، هذا تعريف لـ:",
      "options": [
        "كتب الأطراف",
        "كتب العلل",
        "كتب المسانيد",
        "كتب الجوامع"
      ],
      "correctAnswer": 0
    },
    {
      "id": 48,
      "text": "ما هي الملاحظة الأبرز على \"سنن ابن ماجه\" من حيث الأحاديث التي يحتويها؟",
      "options": [
        "يخلو تماماً من الأحاديث الضعيفة",
        "يحتوي على أحاديث ضعيفة كثيرة (نحو الألف)",
        "جميع أحاديثه في درجة الحسن",
        "يقتصر على الأحاديث المخرجة في الصحيحين"
      ],
      "correctAnswer": 1
    },
    {
      "id": 49,
      "text": "\"جامع جيد كثير الأبواب والغرائب\"، هو وصف قاله ابن حجر عن كتاب:",
      "options": [
        "سنن أبي داود",
        "جامع الترمذي",
        "سنن النسائي",
        "سنن ابن ماجه"
      ],
      "correctAnswer": 3
    },
    {
      "id": 50,
      "text": "بلغت أبواب كتاب \"سنن ابن ماجه\" ألفاً وخمسين باباً.",
      "options": [
        "صواب",
        "خطأ"
      ],
      "correctAnswer": 0
    }
  ]
}